miru/__init__.py
miru/__main__.py
miru/button.py
miru/client.py
miru/exceptions.py
miru/modal.py
miru/py.typed
miru/response.py
miru/text_input.py
miru/view.py
miru/abc/__init__.py
miru/abc/context.py
miru/abc/item.py
miru/abc/item_handler.py
miru/abc/select.py
miru/context/__init__.py
miru/context/modal.py
miru/context/view.py
miru/ext/__init__.py
miru/ext/menu/README.md
miru/ext/menu/__init__.py
miru/ext/menu/items.py
miru/ext/menu/menu.py
miru/ext/menu/py.typed
miru/ext/menu/screen.py
miru/ext/nav/README.md
miru/ext/nav/__init__.py
miru/ext/nav/items.py
miru/ext/nav/navigator.py
miru/ext/nav/py.typed
miru/ext/nav/utils/__init__.py
miru/ext/nav/utils/paginator.py
miru/internal/__init__.py
miru/internal/about.py
miru/internal/deprecation.py
miru/internal/types.py
miru/internal/version.py
miru/select/__init__.py
miru/select/channel.py
miru/select/mentionable.py
miru/select/role.py
miru/select/text.py
miru/select/user.py
hikari_miru-4.2.0.dist-info/LICENSE
hikari_miru-4.2.0.dist-info/METADATA
hikari_miru-4.2.0.dist-info/WHEEL
hikari_miru-4.2.0.dist-info/top_level.txt
hikari_miru-4.2.0.dist-info/RECORD
