Metadata-Version: 2.1
Name: hikari-miru
Version: 4.2.0
Summary: An alternative component handler for hikari, inspired by discord.py's views.
Home-page: https://github.com/hypergonial/hikari-miru
Author: hypergonial
Author-email: 46067571+hypergonial@users.noreply.github.com
Maintainer: hypergonial
License: MIT
Classifier: Development Status :: 5 - Production/Stable
Classifier: Framework :: AsyncIO
Classifier: Intended Audience :: Developers
Classifier: Natural Language :: English
Classifier: Topic :: Software Development :: Libraries :: Python Modules
Classifier: Programming Language :: Python :: 3.10
Classifier: Programming Language :: Python :: 3.11
Classifier: Programming Language :: Python :: 3.12
Classifier: Programming Language :: Python :: 3.13
Classifier: Programming Language :: Python :: Implementation :: CPython
Classifier: Programming Language :: Python :: 3 :: Only
Classifier: Topic :: Software Development :: Libraries
Classifier: Topic :: Software Development :: Libraries :: Application Frameworks
Classifier: Topic :: Software Development :: Libraries :: Python Modules
Requires-Python: >=3.10.0,<3.14
License-File: LICENSE
Requires-Dist: hikari >=2.0.0
Requires-Dist: alluka <0.4,>=0.3.0
Requires-Dist: attrs >=23.1
Requires-Dist: colorama ; sys_platform=="win32"
Provides-Extra: dev
Requires-Dist: ruff ==0.6.3 ; extra == 'dev'
Requires-Dist: pyright ==1.1.369 ; extra == 'dev'
Requires-Dist: nox ==2024.4.15 ; extra == 'dev'
Requires-Dist: typing-extensions ==4.12.2 ; extra == 'dev'
Requires-Dist: pytest ==8.3.2 ; extra == 'dev'
Requires-Dist: pytest-asyncio ==0.24.0 ; extra == 'dev'
Requires-Dist: slotscheck ==0.19.0 ; extra == 'dev'
Requires-Dist: hikari-tanjun ==2.17.6 ; extra == 'dev'
Requires-Dist: hikari-arc ==1.4.0 ; extra == 'dev'
Provides-Extra: docs
Requires-Dist: mkdocs-material[imaging] ~=9.5.34 ; extra == 'docs'
Requires-Dist: mkdocs ~=1.6.1 ; extra == 'docs'
Requires-Dist: mkdocstrings-python ~=1.10.9 ; extra == 'docs'
Requires-Dist: black ~=24.8.0 ; extra == 'docs'
Requires-Dist: griffe-inherited-docstrings ~=1.0.0 ; extra == 'docs'
Requires-Dist: mkdocs-glightbox ~=0.4.0 ; extra == 'docs'
